MANIFEST.in
README.rst
setup.py
ddcheck/__init__.py
ddcheck/console.py
ddcheck/dyndns.py
ddcheck/resolver.py
ddcheck/server.py
ddcheck/version.py
ddcheck.egg-info/PKG-INFO
ddcheck.egg-info/SOURCES.txt
ddcheck.egg-info/dependency_links.txt
ddcheck.egg-info/entry_points.txt
ddcheck.egg-info/not-zip-safe
ddcheck.egg-info/requires.txt
ddcheck.egg-info/top_level.txt