Metadata-Version: 1.0
Name: ddcheck
Version: 0.0.1
Summary: Check URLs and manage the respective records in DynDNS.
Home-page: https://github.com/whiskybar/ddcheck
Author: Jiri Barton
Author-email: jbar@tele3.cz
License: BSD
Platform: UNKNOWN
